MANIFEST.in
setup.py
Statobot.egg-info/PKG-INFO
Statobot.egg-info/SOURCES.txt
Statobot.egg-info/dependency_links.txt
Statobot.egg-info/requires.txt
Statobot.egg-info/top_level.txt
statobot/__init__.py
statobot/client.py
statobot/server.py
statobot/service.py
twisted/plugins/statobot_plugin.py