Metadata-Version: 1.0
Name: Statobot
Version: 0.1.1dev
Summary: Stat bot for moniotring servers.
Home-page: UNKNOWN
Author: Jakub Warmuz
Author-email: jakub.warmuz@gmail.com
License: UNKNOWN
Keywords: bot stats unix
Platform: UNKNOWN
